{"ATLAS":{"SPRITES":[{"SPRITE":{"name":"0000","x":1453,"y":570,"w":109,"h":166,"rotated":false}},{"SPRITE":{"name":"0001","x":648,"y":1466,"w":280,"h":300,"rotated":true}},{"SPRITE":{"name":"0002","x":1453,"y":1005,"w":339,"h":379,"rotated":false}},{"SPRITE":{"name":"0003","x":1121,"y":1724,"w":123,"h":177,"rotated":false}},{"SPRITE":{"name":"0004","x":1913,"y":1676,"w":120,"h":201,"rotated":true}},{"SPRITE":{"name":"0005","x":346,"y":1133,"w":298,"h":372,"rotated":false}},{"SPRITE":{"name":"0006","x":346,"y":949,"w":176,"h":155,"rotated":false}},{"SPRITE":{"name":"0007","x":1610,"y":1384,"w":329,"h":292,"rotated":false}},{"SPRITE":{"name":"0008","x":644,"y":1133,"w":286,"h":333,"rotated":true}},{"SPRITE":{"name":"0009","x":1792,"y":1199,"w":195,"h":173,"rotated":true}},{"SPRITE":{"name":"0010","x":933,"y":1102,"w":350,"h":334,"rotated":false}},{"SPRITE":{"name":"0011","x":329,"y":1505,"w":319,"h":287,"rotated":false}},{"SPRITE":{"name":"0012","x":930,"y":1436,"w":324,"h":288,"rotated":false}},{"SPRITE":{"name":"0013","x":928,"y":1724,"w":193,"h":138,"rotated":false}},{"SPRITE":{"name":"0014","x":1254,"y":1689,"w":188,"h":179,"rotated":false}},{"SPRITE":{"name":"0015","x":0,"y":1322,"w":329,"h":309,"rotated":false}},{"SPRITE":{"name":"0016","x":1283,"y":1384,"w":327,"h":305,"rotated":false}},{"SPRITE":{"name":"0017","x":0,"y":603,"w":416,"h":346,"rotated":false}},{"SPRITE":{"name":"0018","x":1792,"y":1005,"w":185,"h":194,"rotated":false}},{"SPRITE":{"name":"0019","x":1442,"y":1689,"w":149,"h":182,"rotated":true}},{"SPRITE":{"name":"0020","x":1610,"y":1676,"w":303,"h":283,"rotated":false}},{"SPRITE":{"name":"0021","x":0,"y":1631,"w":304,"h":283,"rotated":false}},{"SPRITE":{"name":"0022","x":0,"y":949,"w":346,"h":373,"rotated":false}},{"SPRITE":{"name":"0023","x":1283,"y":1102,"w":130,"h":235,"rotated":true}},{"SPRITE":{"name":"0024","x":0,"y":0,"w":526,"h":603,"rotated":false}},{"SPRITE":{"name":"0025","x":0,"y":0,"w":526,"h":603,"rotated":false}},{"SPRITE":{"name":"0026","x":526,"y":0,"w":513,"h":599,"rotated":false}},{"SPRITE":{"name":"0027","x":526,"y":0,"w":513,"h":599,"rotated":false}},{"SPRITE":{"name":"0028","x":526,"y":0,"w":513,"h":599,"rotated":false}},{"SPRITE":{"name":"0029","x":526,"y":0,"w":513,"h":599,"rotated":false}},{"SPRITE":{"name":"0030","x":526,"y":0,"w":513,"h":599,"rotated":false}},{"SPRITE":{"name":"0031","x":526,"y":0,"w":513,"h":599,"rotated":false}},{"SPRITE":{"name":"0032","x":526,"y":0,"w":513,"h":599,"rotated":false}},{"SPRITE":{"name":"0033","x":526,"y":0,"w":513,"h":599,"rotated":false}},{"SPRITE":{"name":"0034","x":526,"y":0,"w":513,"h":599,"rotated":false}},{"SPRITE":{"name":"0035","x":526,"y":0,"w":513,"h":599,"rotated":false}},{"SPRITE":{"name":"0036","x":526,"y":0,"w":513,"h":599,"rotated":false}},{"SPRITE":{"name":"0037","x":526,"y":0,"w":513,"h":599,"rotated":false}},{"SPRITE":{"name":"0038","x":1563,"y":520,"w":464,"h":485,"rotated":false}},{"SPRITE":{"name":"0039","x":1563,"y":0,"w":456,"h":520,"rotated":false}},{"SPRITE":{"name":"0040","x":526,"y":599,"w":407,"h":534,"rotated":false}},{"SPRITE":{"name":"0041","x":1039,"y":570,"w":414,"h":532,"rotated":false}},{"SPRITE":{"name":"0042","x":1039,"y":0,"w":524,"h":570,"rotated":false}}]},"meta":{"app":"Adobe Animate","version":"18.0.2.126","image":"spritemap.png","format":"RGBA8888","size":{"w":2048,"h":2048},"scale":"1"}}